pygments/__init__.py
pygments/__main__.py
pygments/cmdline.py
pygments/console.py
pygments/filter.py
pygments/formatter.py
pygments/lexer.py
pygments/modeline.py
pygments/plugin.py
pygments/regexopt.py
pygments/scanner.py
pygments/sphinxext.py
pygments/style.py
pygments/token.py
pygments/unistring.py
pygments/util.py
pygments/filters/__init__.py
pygments/formatters/__init__.py
pygments/formatters/_mapping.py
pygments/formatters/bbcode.py
pygments/formatters/groff.py
pygments/formatters/html.py
pygments/formatters/img.py
pygments/formatters/irc.py
pygments/formatters/latex.py
pygments/formatters/other.py
pygments/formatters/pangomarkup.py
pygments/formatters/rtf.py
pygments/formatters/svg.py
pygments/formatters/terminal.py
pygments/formatters/terminal256.py
pygments/lexers/__init__.py
pygments/lexers/_ada_builtins.py
pygments/lexers/_asy_builtins.py
pygments/lexers/_cl_builtins.py
pygments/lexers/_cocoa_builtins.py
pygments/lexers/_csound_builtins.py
pygments/lexers/_css_builtins.py
pygments/lexers/_julia_builtins.py
pygments/lexers/_lasso_builtins.py
pygments/lexers/_lilypond_builtins.py
pygments/lexers/_lua_builtins.py
pygments/lexers/_mapping.py
pygments/lexers/_mql_builtins.py
pygments/lexers/_mysql_builtins.py
pygments/lexers/_openedge_builtins.py
pygments/lexers/_php_builtins.py
pygments/lexers/_postgres_builtins.py
pygments/lexers/_qlik_builtins.py
pygments/lexers/_scheme_builtins.py
pygments/lexers/_scilab_builtins.py
pygments/lexers/_sourcemod_builtins.py
pygments/lexers/_stan_builtins.py
pygments/lexers/_stata_builtins.py
pygments/lexers/_tsql_builtins.py
pygments/lexers/_usd_builtins.py
pygments/lexers/_vbscript_builtins.py
pygments/lexers/_vim_builtins.py
pygments/lexers/actionscript.py
pygments/lexers/ada.py
pygments/lexers/agile.py
pygments/lexers/algebra.py
pygments/lexers/ambient.py
pygments/lexers/amdgpu.py
pygments/lexers/ampl.py
pygments/lexers/apdlexer.py
pygments/lexers/apl.py
pygments/lexers/archetype.py
pygments/lexers/arrow.py
Pygments-2.16.0.dist-info/AUTHORS
Pygments-2.16.0.dist-info/LICENSE
Pygments-2.16.0.dist-info/METADATA
Pygments-2.16.0.dist-info/WHEEL
Pygments-2.16.0.dist-info/entry_points.txt
Pygments-2.16.0.dist-info/top_level.txt
Pygments-2.16.0.dist-info/RECORD
